fmfocus/__init__.py
fmfocus/main.py
fmfocus-0.1.0.dist-info/METADATA
fmfocus-0.1.0.dist-info/WHEEL
fmfocus-0.1.0.dist-info/top_level.txt
fmfocus-0.1.0.dist-info/RECORD
