Metadata-Version: 2.1
Name: fmfocus
Version: 0.1.0
Summary: UNKNOWN
Home-page: UNKNOWN
Author: Your Name
Author-email: UNKNOWN
License: UNKNOWN
Platform: UNKNOWN
Requires-Dist: requests
Requires-Dist: beautifulsoup4
Requires-Dist: vidstream
